README.md
requirements.txt
setup.py
xfapi/__init__.py
xfapi/generate.py
xfapi/server.py
xfapi.egg-info/PKG-INFO
xfapi.egg-info/SOURCES.txt
xfapi.egg-info/dependency_links.txt
xfapi.egg-info/entry_points.txt
xfapi.egg-info/requires.txt
xfapi.egg-info/top_level.txt
xfapi/utils/__init__.py
xfapi/utils/auth.py
xfapi/utils/decorator.py
xfapi/utils/load_yaml.py
xfapi/utils/log.py
xfapi/utils/response.py
xfapi/utils/sql_utils.py
xfapi/utils/task.py
xfapi/utils/tools.py