Metadata-Version: 2.1
Name: xfapi
Version: 0.1.8
Summary: Apis tool base fastapi
Home-page: https://pypi.org/project/xfapi/
Author: 孟安乐
Author-email: asiaier@163.com
Classifier: Programming Language :: Python :: 3
Classifier: License :: OSI Approved :: MIT License
Classifier: Operating System :: OS Independent
Requires-Python: >=3.9
Requires-Dist: fastapi
Requires-Dist: uvicorn
Requires-Dist: pyyaml
Requires-Dist: python-jose
Requires-Dist: pymysql
Requires-Dist: dbutils
Requires-Dist: apscheduler
